[
    {
        "currency_name": "JPY",
        "spot_exchange_buying_price": 4.8259,
        "cash_buying_price": 4.8258,
        "spot_selling_price": 4.8583,
        "cash_selling_price": 4.8602,
        "bank_of_china_conversion_price": 4.8116,
        "publish_date": "2023.12.01 23:15:17"
    },
    {
        "currency_name": "JPY",
        "spot_exchange_buying_price": 4.8272,
        "cash_buying_price": 4.8271,
        "spot_selling_price": 4.8596,
        "cash_selling_price": 4.8615,
        "bank_of_china_conversion_price": 4.8116,
        "publish_date": "2023.12.01 23:13:33"
    },
    {
        "currency_name": "JPY",
        "spot_exchange_buying_price": 4.8093,
        "cash_buying_price": 4.8092,
        "spot_selling_price": 4.8415,
        "cash_selling_price": 4.8434,
        "bank_of_china_conversion_price": 4.8116,
        "publish_date": "2023.12.01 22:54:31"
    },
    {
        "currency_name": "JPY",
        "spot_exchange_buying_price": 4.8093,
        "cash_buying_price": 4.8092,
        "spot_selling_price": 4.8415,
        "cash_selling_price": 4.8434,
        "bank_of_china_conversion_price": 4.8116,
        "publish_date": "2023.12.01 22:52:36"
    },
    {
        "currency_name": "JPY",
        "spot_exchange_buying_price": 4.8054,
        "cash_buying_price": 4.8053,
        "spot_selling_price": 4.8376,
        "cash_selling_price": 4.8395,
        "bank_of_china_conversion_price": 4.8116,
        "publish_date": "2023.12.01 22:15:29"
    },
    {
        "currency_name": "JPY",
        "spot_exchange_buying_price": 4.8074,
        "cash_buying_price": 4.8073,
        "spot_selling_price": 4.8396,
        "cash_selling_price": 4.8415,
        "bank_of_china_conversion_price": 4.8116,
        "publish_date": "2023.12.01 21:49:55"
    },
    {
        "currency_name": "JPY",
        "spot_exchange_buying_price": 4.8074,
        "cash_buying_price": 4.8073,
        "spot_selling_price": 4.8396,
        "cash_selling_price": 4.8415,
        "bank_of_china_conversion_price": 4.8116,
        "publish_date": "2023.12.01 21:33:59"
    },
    {
        "currency_name": "JPY",
        "spot_exchange_buying_price": 4.8093,
        "cash_buying_price": 4.8092,
        "spot_selling_price": 4.8415,
        "cash_selling_price": 4.8434,
        "bank_of_china_conversion_price": 4.8116,
        "publish_date": "2023.12.01 21:19:46"
    },
    {
        "currency_name": "JPY",
        "spot_exchange_buying_price": 4.8057,
        "cash_buying_price": 4.8056,
        "spot_selling_price": 4.8379,
        "cash_selling_price": 4.8398,
        "bank_of_china_conversion_price": 4.8116,
        "publish_date": "2023.12.01 21:08:27"
    },
    {
        "currency_name": "JPY",
        "spot_exchange_buying_price": 4.8051,
        "cash_buying_price": 4.805,
        "spot_selling_price": 4.8373,
        "cash_selling_price": 4.8392,
        "bank_of_china_conversion_price": 4.8116,
        "publish_date": "2023.12.01 21:07:28"
    },
    {
        "currency_name": "JPY",
        "spot_exchange_buying_price": 4.8034,
        "cash_buying_price": 4.8033,
        "spot_selling_price": 4.8356,
        "cash_selling_price": 4.8375,
        "bank_of_china_conversion_price": 4.8116,
        "publish_date": "2023.12.01 21:01:59"
    },
    {
        "currency_name": "JPY",
        "spot_exchange_buying_price": 4.8018,
        "cash_buying_price": 4.8017,
        "spot_selling_price": 4.834,
        "cash_selling_price": 4.8359,
        "bank_of_china_conversion_price": 4.8116,
        "publish_date": "2023.12.01 20:51:58"
    },
    {
        "currency_name": "JPY",
        "spot_exchange_buying_price": 4.8051,
        "cash_buying_price": 4.805,
        "spot_selling_price": 4.8373,
        "cash_selling_price": 4.8392,
        "bank_of_china_conversion_price": 4.8116,
        "publish_date": "2023.12.01 20:47:18"
    },
    {
        "currency_name": "JPY",
        "spot_exchange_buying_price": 4.8093,
        "cash_buying_price": 4.8092,
        "spot_selling_price": 4.8415,
        "cash_selling_price": 4.8434,
        "bank_of_china_conversion_price": 4.8116,
        "publish_date": "2023.12.01 20:33:05"
    },
    {
        "currency_name": "JPY",
        "spot_exchange_buying_price": 4.8054,
        "cash_buying_price": 4.8053,
        "spot_selling_price": 4.8376,
        "cash_selling_price": 4.8395,
        "bank_of_china_conversion_price": 4.8116,
        "publish_date": "2023.12.01 20:14:29"
    },
    {
        "currency_name": "JPY",
        "spot_exchange_buying_price": 4.8063,
        "cash_buying_price": 4.8062,
        "spot_selling_price": 4.8385,
        "cash_selling_price": 4.8404,
        "bank_of_china_conversion_price": 4.8116,
        "publish_date": "2023.12.01 19:51:16"
    },
    {
        "currency_name": "JPY",
        "spot_exchange_buying_price": 4.806,
        "cash_buying_price": 4.8059,
        "spot_selling_price": 4.8382,
        "cash_selling_price": 4.8401,
        "bank_of_china_conversion_price": 4.8116,
        "publish_date": "2023.12.01 19:39:29"
    },
    {
        "currency_name": "JPY",
        "spot_exchange_buying_price": 4.8109,
        "cash_buying_price": 4.8108,
        "spot_selling_price": 4.8431,
        "cash_selling_price": 4.845,
        "bank_of_china_conversion_price": 4.8116,
        "publish_date": "2023.12.01 19:19:14"
    },
    {
        "currency_name": "JPY",
        "spot_exchange_buying_price": 4.8109,
        "cash_buying_price": 4.8108,
        "spot_selling_price": 4.8431,
        "cash_selling_price": 4.845,
        "bank_of_china_conversion_price": 4.8116,
        "publish_date": "2023.12.01 19:06:46"
    },
    {
        "currency_name": "JPY",
        "spot_exchange_buying_price": 4.8109,
        "cash_buying_price": 4.8108,
        "spot_selling_price": 4.8431,
        "cash_selling_price": 4.845,
        "bank_of_china_conversion_price": 4.8116,
        "publish_date": "2023.12.01 18:53:56"
    },
    {
        "currency_name": "JPY",
        "spot_exchange_buying_price": 4.8096,
        "cash_buying_price": 4.8095,
        "spot_selling_price": 4.8418,
        "cash_selling_price": 4.8437,
        "bank_of_china_conversion_price": 4.8116,
        "publish_date": "2023.12.01 18:47:40"
    },
    {
        "currency_name": "JPY",
        "spot_exchange_buying_price": 4.8092,
        "cash_buying_price": 4.8091,
        "spot_selling_price": 4.8414,
        "cash_selling_price": 4.8433,
        "bank_of_china_conversion_price": 4.8116,
        "publish_date": "2023.12.01 18:45:57"
    },
    {
        "currency_name": "JPY",
        "spot_exchange_buying_price": 4.8092,
        "cash_buying_price": 4.8091,
        "spot_selling_price": 4.8414,
        "cash_selling_price": 4.8433,
        "bank_of_china_conversion_price": 4.8116,
        "publish_date": "2023.12.01 18:45:41"
    },
    {
        "currency_name": "JPY",
        "spot_exchange_buying_price": 4.8092,
        "cash_buying_price": 4.8091,
        "spot_selling_price": 4.8414,
        "cash_selling_price": 4.8433,
        "bank_of_china_conversion_price": 4.8116,
        "publish_date": "2023.12.01 18:44:00"
    },
    {
        "currency_name": "JPY",
        "spot_exchange_buying_price": 4.8086,
        "cash_buying_price": 4.8085,
        "spot_selling_price": 4.8408,
        "cash_selling_price": 4.8427,
        "bank_of_china_conversion_price": 4.8116,
        "publish_date": "2023.12.01 18:43:00"
    },
    {
        "currency_name": "JPY",
        "spot_exchange_buying_price": 4.8086,
        "cash_buying_price": 4.8085,
        "spot_selling_price": 4.8408,
        "cash_selling_price": 4.8427,
        "bank_of_china_conversion_price": 4.8116,
        "publish_date": "2023.12.01 18:41:49"
    },
    {
        "currency_name": "JPY",
        "spot_exchange_buying_price": 4.8092,
        "cash_buying_price": 4.8091,
        "spot_selling_price": 4.8414,
        "cash_selling_price": 4.8433,
        "bank_of_china_conversion_price": 4.8116,
        "publish_date": "2023.12.01 18:39:28"
    },
    {
        "currency_name": "JPY",
        "spot_exchange_buying_price": 4.8099,
        "cash_buying_price": 4.8098,
        "spot_selling_price": 4.8421,
        "cash_selling_price": 4.844,
        "bank_of_china_conversion_price": 4.8116,
        "publish_date": "2023.12.01 18:35:43"
    },
    {
        "currency_name": "JPY",
        "spot_exchange_buying_price": 4.8105,
        "cash_buying_price": 4.8104,
        "spot_selling_price": 4.8427,
        "cash_selling_price": 4.8446,
        "bank_of_china_conversion_price": 4.8116,
        "publish_date": "2023.12.01 18:35:03"
    },
    {
        "currency_name": "JPY",
        "spot_exchange_buying_price": 4.8112,
        "cash_buying_price": 4.8111,
        "spot_selling_price": 4.8434,
        "cash_selling_price": 4.8453,
        "bank_of_china_conversion_price": 4.8116,
        "publish_date": "2023.12.01 18:28:10"
    },
    {
        "currency_name": "JPY",
        "spot_exchange_buying_price": 4.8112,
        "cash_buying_price": 4.8111,
        "spot_selling_price": 4.8434,
        "cash_selling_price": 4.8453,
        "bank_of_china_conversion_price": 4.8116,
        "publish_date": "2023.12.01 18:21:44"
    },
    {
        "currency_name": "JPY",
        "spot_exchange_buying_price": 4.8125,
        "cash_buying_price": 4.8124,
        "spot_selling_price": 4.8447,
        "cash_selling_price": 4.8466,
        "bank_of_china_conversion_price": 4.8116,
        "publish_date": "2023.12.01 18:17:50"
    },
    {
        "currency_name": "JPY",
        "spot_exchange_buying_price": 4.8125,
        "cash_buying_price": 4.8124,
        "spot_selling_price": 4.8447,
        "cash_selling_price": 4.8466,
        "bank_of_china_conversion_price": 4.8116,
        "publish_date": "2023.12.01 18:15:04"
    },
    {
        "currency_name": "JPY",
        "spot_exchange_buying_price": 4.8121,
        "cash_buying_price": 4.812,
        "spot_selling_price": 4.8443,
        "cash_selling_price": 4.8462,
        "bank_of_china_conversion_price": 4.8116,
        "publish_date": "2023.12.01 18:13:33"
    },
    {
        "currency_name": "JPY",
        "spot_exchange_buying_price": 4.8144,
        "cash_buying_price": 4.8143,
        "spot_selling_price": 4.8466,
        "cash_selling_price": 4.8486,
        "bank_of_china_conversion_price": 4.8116,
        "publish_date": "2023.12.01 18:10:09"
    },
    {
        "currency_name": "JPY",
        "spot_exchange_buying_price": 4.8141,
        "cash_buying_price": 4.814,
        "spot_selling_price": 4.8463,
        "cash_selling_price": 4.8483,
        "bank_of_china_conversion_price": 4.8116,
        "publish_date": "2023.12.01 18:09:48"
    },
    {
        "currency_name": "JPY",
        "spot_exchange_buying_price": 4.8134,
        "cash_buying_price": 4.8133,
        "spot_selling_price": 4.8456,
        "cash_selling_price": 4.8476,
        "bank_of_china_conversion_price": 4.8116,
        "publish_date": "2023.12.01 18:06:27"
    },
    {
        "currency_name": "JPY",
        "spot_exchange_buying_price": 4.8121,
        "cash_buying_price": 4.812,
        "spot_selling_price": 4.8443,
        "cash_selling_price": 4.8462,
        "bank_of_china_conversion_price": 4.8116,
        "publish_date": "2023.12.01 18:01:12"
    },
    {
        "currency_name": "JPY",
        "spot_exchange_buying_price": 4.8157,
        "cash_buying_price": 4.8156,
        "spot_selling_price": 4.8479,
        "cash_selling_price": 4.8499,
        "bank_of_china_conversion_price": 4.8116,
        "publish_date": "2023.12.01 17:37:16"
    },
    {
        "currency_name": "JPY",
        "spot_exchange_buying_price": 4.8163,
        "cash_buying_price": 4.8162,
        "spot_selling_price": 4.8485,
        "cash_selling_price": 4.8505,
        "bank_of_china_conversion_price": 4.8116,
        "publish_date": "2023.12.01 17:33:53"
    },
    {
        "currency_name": "JPY",
        "spot_exchange_buying_price": 4.816,
        "cash_buying_price": 4.8159,
        "spot_selling_price": 4.8482,
        "cash_selling_price": 4.8502,
        "bank_of_china_conversion_price": 4.8116,
        "publish_date": "2023.12.01 17:32:48"
    },
    {
        "currency_name": "JPY",
        "spot_exchange_buying_price": 4.8161,
        "cash_buying_price": 4.816,
        "spot_selling_price": 4.8483,
        "cash_selling_price": 4.8503,
        "bank_of_china_conversion_price": 4.8116,
        "publish_date": "2023.12.01 17:28:55"
    },
    {
        "currency_name": "JPY",
        "spot_exchange_buying_price": 4.8148,
        "cash_buying_price": 4.8147,
        "spot_selling_price": 4.847,
        "cash_selling_price": 4.849,
        "bank_of_china_conversion_price": 4.8116,
        "publish_date": "2023.12.01 17:20:20"
    },
    {
        "currency_name": "JPY",
        "spot_exchange_buying_price": 4.8154,
        "cash_buying_price": 4.8153,
        "spot_selling_price": 4.8476,
        "cash_selling_price": 4.8496,
        "bank_of_china_conversion_price": 4.8116,
        "publish_date": "2023.12.01 17:15:44"
    },
    {
        "currency_name": "JPY",
        "spot_exchange_buying_price": 4.8151,
        "cash_buying_price": 4.815,
        "spot_selling_price": 4.8473,
        "cash_selling_price": 4.8493,
        "bank_of_china_conversion_price": 4.8116,
        "publish_date": "2023.12.01 17:14:57"
    },
    {
        "currency_name": "JPY",
        "spot_exchange_buying_price": 4.8128,
        "cash_buying_price": 4.8127,
        "spot_selling_price": 4.845,
        "cash_selling_price": 4.8469,
        "bank_of_china_conversion_price": 4.8116,
        "publish_date": "2023.12.01 16:53:13"
    },
    {
        "currency_name": "JPY",
        "spot_exchange_buying_price": 4.8112,
        "cash_buying_price": 4.8111,
        "spot_selling_price": 4.8434,
        "cash_selling_price": 4.8453,
        "bank_of_china_conversion_price": 4.8116,
        "publish_date": "2023.12.01 16:48:31"
    },
    {
        "currency_name": "JPY",
        "spot_exchange_buying_price": 4.8122,
        "cash_buying_price": 4.8121,
        "spot_selling_price": 4.8444,
        "cash_selling_price": 4.8463,
        "bank_of_china_conversion_price": 4.8116,
        "publish_date": "2023.12.01 16:47:21"
    },
    {
        "currency_name": "JPY",
        "spot_exchange_buying_price": 4.8099,
        "cash_buying_price": 4.8098,
        "spot_selling_price": 4.8421,
        "cash_selling_price": 4.844,
        "bank_of_china_conversion_price": 4.8116,
        "publish_date": "2023.12.01 16:38:48"
    },
    {
        "currency_name": "JPY",
        "spot_exchange_buying_price": 4.8087,
        "cash_buying_price": 4.8086,
        "spot_selling_price": 4.8409,
        "cash_selling_price": 4.8428,
        "bank_of_china_conversion_price": 4.8116,
        "publish_date": "2023.12.01 16:35:43"
    },
    {
        "currency_name": "JPY",
        "spot_exchange_buying_price": 4.8057,
        "cash_buying_price": 4.8056,
        "spot_selling_price": 4.8379,
        "cash_selling_price": 4.8398,
        "bank_of_china_conversion_price": 4.8116,
        "publish_date": "2023.12.01 16:30:45"
    },
    {
        "currency_name": "JPY",
        "spot_exchange_buying_price": 4.8047,
        "cash_buying_price": 4.8046,
        "spot_selling_price": 4.8369,
        "cash_selling_price": 4.8388,
        "bank_of_china_conversion_price": 4.8116,
        "publish_date": "2023.12.01 16:29:56"
    },
    {
        "currency_name": "JPY",
        "spot_exchange_buying_price": 4.8047,
        "cash_buying_price": 4.8046,
        "spot_selling_price": 4.8369,
        "cash_selling_price": 4.8388,
        "bank_of_china_conversion_price": 4.8116,
        "publish_date": "2023.12.01 16:28:44"
    },
    {
        "currency_name": "JPY",
        "spot_exchange_buying_price": 4.807,
        "cash_buying_price": 4.8069,
        "spot_selling_price": 4.8392,
        "cash_selling_price": 4.8411,
        "bank_of_china_conversion_price": 4.8116,
        "publish_date": "2023.12.01 16:27:40"
    },
    {
        "currency_name": "JPY",
        "spot_exchange_buying_price": 4.8073,
        "cash_buying_price": 4.8072,
        "spot_selling_price": 4.8395,
        "cash_selling_price": 4.8414,
        "bank_of_china_conversion_price": 4.8116,
        "publish_date": "2023.12.01 16:25:03"
    },
    {
        "currency_name": "JPY",
        "spot_exchange_buying_price": 4.8064,
        "cash_buying_price": 4.8063,
        "spot_selling_price": 4.8386,
        "cash_selling_price": 4.8405,
        "bank_of_china_conversion_price": 4.8116,
        "publish_date": "2023.12.01 16:18:26"
    },
    {
        "currency_name": "JPY",
        "spot_exchange_buying_price": 4.8041,
        "cash_buying_price": 4.804,
        "spot_selling_price": 4.8363,
        "cash_selling_price": 4.8382,
        "bank_of_china_conversion_price": 4.8116,
        "publish_date": "2023.12.01 16:11:44"
    },
    {
        "currency_name": "JPY",
        "spot_exchange_buying_price": 4.8051,
        "cash_buying_price": 4.805,
        "spot_selling_price": 4.8373,
        "cash_selling_price": 4.8392,
        "bank_of_china_conversion_price": 4.8116,
        "publish_date": "2023.12.01 16:08:59"
    },
    {
        "currency_name": "JPY",
        "spot_exchange_buying_price": 4.8041,
        "cash_buying_price": 4.804,
        "spot_selling_price": 4.8363,
        "cash_selling_price": 4.8382,
        "bank_of_china_conversion_price": 4.8116,
        "publish_date": "2023.12.01 15:57:36"
    },
    {
        "currency_name": "JPY",
        "spot_exchange_buying_price": 4.8035,
        "cash_buying_price": 4.8034,
        "spot_selling_price": 4.8357,
        "cash_selling_price": 4.8376,
        "bank_of_china_conversion_price": 4.8116,
        "publish_date": "2023.12.01 15:55:21"
    },
    {
        "currency_name": "JPY",
        "spot_exchange_buying_price": 4.8034,
        "cash_buying_price": 4.8033,
        "spot_selling_price": 4.8356,
        "cash_selling_price": 4.8375,
        "bank_of_china_conversion_price": 4.8116,
        "publish_date": "2023.12.01 15:52:25"
    },
    {
        "currency_name": "JPY",
        "spot_exchange_buying_price": 4.8041,
        "cash_buying_price": 4.804,
        "spot_selling_price": 4.8363,
        "cash_selling_price": 4.8382,
        "bank_of_china_conversion_price": 4.8116,
        "publish_date": "2023.12.01 15:50:10"
    },
    {
        "currency_name": "JPY",
        "spot_exchange_buying_price": 4.8077,
        "cash_buying_price": 4.8076,
        "spot_selling_price": 4.8399,
        "cash_selling_price": 4.8418,
        "bank_of_china_conversion_price": 4.8116,
        "publish_date": "2023.12.01 15:45:23"
    },
    {
        "currency_name": "JPY",
        "spot_exchange_buying_price": 4.8067,
        "cash_buying_price": 4.8066,
        "spot_selling_price": 4.8389,
        "cash_selling_price": 4.8408,
        "bank_of_china_conversion_price": 4.8116,
        "publish_date": "2023.12.01 15:42:43"
    },
    {
        "currency_name": "JPY",
        "spot_exchange_buying_price": 4.809,
        "cash_buying_price": 4.8089,
        "spot_selling_price": 4.8412,
        "cash_selling_price": 4.8431,
        "bank_of_china_conversion_price": 4.8116,
        "publish_date": "2023.12.01 15:40:13"
    },
    {
        "currency_name": "JPY",
        "spot_exchange_buying_price": 4.8087,
        "cash_buying_price": 4.8086,
        "spot_selling_price": 4.8409,
        "cash_selling_price": 4.8428,
        "bank_of_china_conversion_price": 4.8116,
        "publish_date": "2023.12.01 15:30:22"
    },
    {
        "currency_name": "JPY",
        "spot_exchange_buying_price": 4.809,
        "cash_buying_price": 4.8089,
        "spot_selling_price": 4.8412,
        "cash_selling_price": 4.8431,
        "bank_of_china_conversion_price": 4.8116,
        "publish_date": "2023.12.01 15:28:47"
    },
    {
        "currency_name": "JPY",
        "spot_exchange_buying_price": 4.8097,
        "cash_buying_price": 4.8096,
        "spot_selling_price": 4.8419,
        "cash_selling_price": 4.8438,
        "bank_of_china_conversion_price": 4.8116,
        "publish_date": "2023.12.01 15:17:17"
    },
    {
        "currency_name": "JPY",
        "spot_exchange_buying_price": 4.8067,
        "cash_buying_price": 4.8066,
        "spot_selling_price": 4.8389,
        "cash_selling_price": 4.8408,
        "bank_of_china_conversion_price": 4.8116,
        "publish_date": "2023.12.01 15:14:44"
    },
    {
        "currency_name": "JPY",
        "spot_exchange_buying_price": 4.8074,
        "cash_buying_price": 4.8073,
        "spot_selling_price": 4.8396,
        "cash_selling_price": 4.8415,
        "bank_of_china_conversion_price": 4.8116,
        "publish_date": "2023.12.01 15:12:07"
    },
    {
        "currency_name": "JPY",
        "spot_exchange_buying_price": 4.8094,
        "cash_buying_price": 4.8093,
        "spot_selling_price": 4.8416,
        "cash_selling_price": 4.8435,
        "bank_of_china_conversion_price": 4.8116,
        "publish_date": "2023.12.01 15:07:24"
    },
    {
        "currency_name": "JPY",
        "spot_exchange_buying_price": 4.8094,
        "cash_buying_price": 4.8093,
        "spot_selling_price": 4.8416,
        "cash_selling_price": 4.8435,
        "bank_of_china_conversion_price": 4.8116,
        "publish_date": "2023.12.01 15:04:31"
    },
    {
        "currency_name": "JPY",
        "spot_exchange_buying_price": 4.8084,
        "cash_buying_price": 4.8083,
        "spot_selling_price": 4.8406,
        "cash_selling_price": 4.8425,
        "bank_of_china_conversion_price": 4.8116,
        "publish_date": "2023.12.01 15:02:15"
    },
    {
        "currency_name": "JPY",
        "spot_exchange_buying_price": 4.8064,
        "cash_buying_price": 4.8063,
        "spot_selling_price": 4.8386,
        "cash_selling_price": 4.8405,
        "bank_of_china_conversion_price": 4.8116,
        "publish_date": "2023.12.01 15:00:49"
    },
    {
        "currency_name": "JPY",
        "spot_exchange_buying_price": 4.8067,
        "cash_buying_price": 4.8066,
        "spot_selling_price": 4.8389,
        "cash_selling_price": 4.8408,
        "bank_of_china_conversion_price": 4.8116,
        "publish_date": "2023.12.01 14:57:58"
    },
    {
        "currency_name": "JPY",
        "spot_exchange_buying_price": 4.8057,
        "cash_buying_price": 4.8056,
        "spot_selling_price": 4.8379,
        "cash_selling_price": 4.8398,
        "bank_of_china_conversion_price": 4.8116,
        "publish_date": "2023.12.01 14:56:23"
    },
    {
        "currency_name": "JPY",
        "spot_exchange_buying_price": 4.8037,
        "cash_buying_price": 4.8036,
        "spot_selling_price": 4.8359,
        "cash_selling_price": 4.8378,
        "bank_of_china_conversion_price": 4.8116,
        "publish_date": "2023.12.01 14:52:15"
    },
    {
        "currency_name": "JPY",
        "spot_exchange_buying_price": 4.8044,
        "cash_buying_price": 4.8043,
        "spot_selling_price": 4.8366,
        "cash_selling_price": 4.8385,
        "bank_of_china_conversion_price": 4.8116,
        "publish_date": "2023.12.01 14:50:14"
    },
    {
        "currency_name": "JPY",
        "spot_exchange_buying_price": 4.8037,
        "cash_buying_price": 4.8036,
        "spot_selling_price": 4.8359,
        "cash_selling_price": 4.8378,
        "bank_of_china_conversion_price": 4.8116,
        "publish_date": "2023.12.01 14:44:32"
    },
    {
        "currency_name": "JPY",
        "spot_exchange_buying_price": 4.8086,
        "cash_buying_price": 4.8085,
        "spot_selling_price": 4.8408,
        "cash_selling_price": 4.8427,
        "bank_of_china_conversion_price": 4.8116,
        "publish_date": "2023.12.01 14:23:27"
    },
    {
        "currency_name": "JPY",
        "spot_exchange_buying_price": 4.8086,
        "cash_buying_price": 4.8085,
        "spot_selling_price": 4.8408,
        "cash_selling_price": 4.8427,
        "bank_of_china_conversion_price": 4.8116,
        "publish_date": "2023.12.01 14:12:10"
    },
    {
        "currency_name": "JPY",
        "spot_exchange_buying_price": 4.8081,
        "cash_buying_price": 4.808,
        "spot_selling_price": 4.8403,
        "cash_selling_price": 4.8422,
        "bank_of_china_conversion_price": 4.8116,
        "publish_date": "2023.12.01 14:02:30"
    },
    {
        "currency_name": "JPY",
        "spot_exchange_buying_price": 4.8082,
        "cash_buying_price": 4.8081,
        "spot_selling_price": 4.8404,
        "cash_selling_price": 4.8423,
        "bank_of_china_conversion_price": 4.8116,
        "publish_date": "2023.12.01 13:52:45"
    },
    {
        "currency_name": "JPY",
        "spot_exchange_buying_price": 4.8082,
        "cash_buying_price": 4.8081,
        "spot_selling_price": 4.8404,
        "cash_selling_price": 4.8423,
        "bank_of_china_conversion_price": 4.8116,
        "publish_date": "2023.12.01 13:51:00"
    },
    {
        "currency_name": "JPY",
        "spot_exchange_buying_price": 4.8076,
        "cash_buying_price": 4.8075,
        "spot_selling_price": 4.8398,
        "cash_selling_price": 4.8417,
        "bank_of_china_conversion_price": 4.8116,
        "publish_date": "2023.12.01 13:48:01"
    },
    {
        "currency_name": "JPY",
        "spot_exchange_buying_price": 4.8076,
        "cash_buying_price": 4.8075,
        "spot_selling_price": 4.8398,
        "cash_selling_price": 4.8417,
        "bank_of_china_conversion_price": 4.8116,
        "publish_date": "2023.12.01 13:35:50"
    },
    {
        "currency_name": "JPY",
        "spot_exchange_buying_price": 4.8073,
        "cash_buying_price": 4.8072,
        "spot_selling_price": 4.8395,
        "cash_selling_price": 4.8414,
        "bank_of_china_conversion_price": 4.8116,
        "publish_date": "2023.12.01 13:33:46"
    },
    {
        "currency_name": "JPY",
        "spot_exchange_buying_price": 4.806,
        "cash_buying_price": 4.8059,
        "spot_selling_price": 4.8382,
        "cash_selling_price": 4.8401,
        "bank_of_china_conversion_price": 4.8116,
        "publish_date": "2023.12.01 13:19:58"
    },
    {
        "currency_name": "JPY",
        "spot_exchange_buying_price": 4.8069,
        "cash_buying_price": 4.8068,
        "spot_selling_price": 4.8391,
        "cash_selling_price": 4.841,
        "bank_of_china_conversion_price": 4.8116,
        "publish_date": "2023.12.01 13:11:43"
    },
    {
        "currency_name": "JPY",
        "spot_exchange_buying_price": 4.8066,
        "cash_buying_price": 4.8065,
        "spot_selling_price": 4.8388,
        "cash_selling_price": 4.8407,
        "bank_of_china_conversion_price": 4.8116,
        "publish_date": "2023.12.01 13:03:39"
    },
    {
        "currency_name": "JPY",
        "spot_exchange_buying_price": 4.8046,
        "cash_buying_price": 4.8045,
        "spot_selling_price": 4.8368,
        "cash_selling_price": 4.8387,
        "bank_of_china_conversion_price": 4.8116,
        "publish_date": "2023.12.01 12:01:05"
    },
    {
        "currency_name": "JPY",
        "spot_exchange_buying_price": 4.804,
        "cash_buying_price": 4.8039,
        "spot_selling_price": 4.8362,
        "cash_selling_price": 4.8381,
        "bank_of_china_conversion_price": 4.8116,
        "publish_date": "2023.12.01 11:53:20"
    },
    {
        "currency_name": "JPY",
        "spot_exchange_buying_price": 4.8078,
        "cash_buying_price": 4.8077,
        "spot_selling_price": 4.84,
        "cash_selling_price": 4.8419,
        "bank_of_china_conversion_price": 4.8116,
        "publish_date": "2023.12.01 11:30:36"
    },
    {
        "currency_name": "JPY",
        "spot_exchange_buying_price": 4.8069,
        "cash_buying_price": 4.8068,
        "spot_selling_price": 4.8391,
        "cash_selling_price": 4.841,
        "bank_of_china_conversion_price": 4.8116,
        "publish_date": "2023.12.01 11:12:56"
    },
    {
        "currency_name": "JPY",
        "spot_exchange_buying_price": 4.8085,
        "cash_buying_price": 4.8084,
        "spot_selling_price": 4.8407,
        "cash_selling_price": 4.8426,
        "bank_of_china_conversion_price": 4.8116,
        "publish_date": "2023.12.01 11:02:50"
    },
    {
        "currency_name": "JPY",
        "spot_exchange_buying_price": 4.8092,
        "cash_buying_price": 4.8091,
        "spot_selling_price": 4.8414,
        "cash_selling_price": 4.8433,
        "bank_of_china_conversion_price": 4.8116,
        "publish_date": "2023.12.01 10:55:56"
    },
    {
        "currency_name": "JPY",
        "spot_exchange_buying_price": 4.8111,
        "cash_buying_price": 4.811,
        "spot_selling_price": 4.8433,
        "cash_selling_price": 4.8452,
        "bank_of_china_conversion_price": 4.8116,
        "publish_date": "2023.12.01 10:46:33"
    },
    {
        "currency_name": "JPY",
        "spot_exchange_buying_price": 4.8107,
        "cash_buying_price": 4.8106,
        "spot_selling_price": 4.8429,
        "cash_selling_price": 4.8448,
        "bank_of_china_conversion_price": 4.8116,
        "publish_date": "2023.12.01 10:45:26"
    },
    {
        "currency_name": "JPY",
        "spot_exchange_buying_price": 4.814,
        "cash_buying_price": 4.8139,
        "spot_selling_price": 4.8462,
        "cash_selling_price": 4.8482,
        "bank_of_china_conversion_price": 4.8116,
        "publish_date": "2023.12.01 10:33:53"
    },
    {
        "currency_name": "JPY",
        "spot_exchange_buying_price": 4.8124,
        "cash_buying_price": 4.8123,
        "spot_selling_price": 4.8446,
        "cash_selling_price": 4.8465,
        "bank_of_china_conversion_price": 4.8116,
        "publish_date": "2023.12.01 10:30:00"
    },
    {
        "currency_name": "JPY",
        "spot_exchange_buying_price": 4.8124,
        "cash_buying_price": 4.8123,
        "spot_selling_price": 4.8446,
        "cash_selling_price": 4.8465,
        "bank_of_china_conversion_price": 4.8116,
        "publish_date": "2023.12.01 10:20:45"
    },
    {
        "currency_name": "JPY",
        "spot_exchange_buying_price": 4.8124,
        "cash_buying_price": 4.8123,
        "spot_selling_price": 4.8446,
        "cash_selling_price": 4.8465,
        "bank_of_china_conversion_price": 4.8116,
        "publish_date": "2023.12.01 10:15:39"
    },
    {
        "currency_name": "JPY",
        "spot_exchange_buying_price": 4.8153,
        "cash_buying_price": 4.8152,
        "spot_selling_price": 4.8475,
        "cash_selling_price": 4.8495,
        "bank_of_china_conversion_price": 4.8116,
        "publish_date": "2023.12.01 10:11:29"
    },
    {
        "currency_name": "JPY",
        "spot_exchange_buying_price": 4.8153,
        "cash_buying_price": 4.8152,
        "spot_selling_price": 4.8475,
        "cash_selling_price": 4.8495,
        "bank_of_china_conversion_price": 4.8116,
        "publish_date": "2023.12.01 10:10:27"
    },
    {
        "currency_name": "JPY",
        "spot_exchange_buying_price": 4.8153,
        "cash_buying_price": 4.8152,
        "spot_selling_price": 4.8475,
        "cash_selling_price": 4.8495,
        "bank_of_china_conversion_price": 4.8116,
        "publish_date": "2023.12.01 10:10:15"
    },
    {
        "currency_name": "JPY",
        "spot_exchange_buying_price": 4.8153,
        "cash_buying_price": 4.8152,
        "spot_selling_price": 4.8475,
        "cash_selling_price": 4.8495,
        "bank_of_china_conversion_price": 4.8116,
        "publish_date": "2023.12.01 10:01:51"
    },
    {
        "currency_name": "JPY",
        "spot_exchange_buying_price": 4.8146,
        "cash_buying_price": 4.8145,
        "spot_selling_price": 4.8468,
        "cash_selling_price": 4.8488,
        "bank_of_china_conversion_price": 4.8116,
        "publish_date": "2023.12.01 09:59:08"
    },
    {
        "currency_name": "JPY",
        "spot_exchange_buying_price": 4.8113,
        "cash_buying_price": 4.8112,
        "spot_selling_price": 4.8435,
        "cash_selling_price": 4.8454,
        "bank_of_china_conversion_price": 4.8116,
        "publish_date": "2023.12.01 09:51:06"
    },
    {
        "currency_name": "JPY",
        "spot_exchange_buying_price": 4.8119,
        "cash_buying_price": 4.8118,
        "spot_selling_price": 4.8441,
        "cash_selling_price": 4.846,
        "bank_of_china_conversion_price": 4.8116,
        "publish_date": "2023.12.01 09:47:48"
    },
    {
        "currency_name": "JPY",
        "spot_exchange_buying_price": 4.8112,
        "cash_buying_price": 4.8111,
        "spot_selling_price": 4.8434,
        "cash_selling_price": 4.8453,
        "bank_of_china_conversion_price": 4.8116,
        "publish_date": "2023.12.01 09:46:38"
    },
    {
        "currency_name": "JPY",
        "spot_exchange_buying_price": 4.8136,
        "cash_buying_price": 4.8135,
        "spot_selling_price": 4.8458,
        "cash_selling_price": 4.8478,
        "bank_of_china_conversion_price": 4.8116,
        "publish_date": "2023.12.01 09:44:31"
    },
    {
        "currency_name": "JPY",
        "spot_exchange_buying_price": 4.8136,
        "cash_buying_price": 4.8135,
        "spot_selling_price": 4.8458,
        "cash_selling_price": 4.8478,
        "bank_of_china_conversion_price": 4.8116,
        "publish_date": "2023.12.01 09:42:40"
    },
    {
        "currency_name": "JPY",
        "spot_exchange_buying_price": 4.8165,
        "cash_buying_price": 4.8165,
        "spot_selling_price": 4.8488,
        "cash_selling_price": 4.8508,
        "bank_of_china_conversion_price": 4.8116,
        "publish_date": "2023.12.01 09:35:58"
    },
    {
        "currency_name": "JPY",
        "spot_exchange_buying_price": 4.8169,
        "cash_buying_price": 4.8169,
        "spot_selling_price": 4.8492,
        "cash_selling_price": 4.8512,
        "bank_of_china_conversion_price": 4.8116,
        "publish_date": "2023.12.01 09:33:28"
    },
    {
        "currency_name": "JPY",
        "spot_exchange_buying_price": 4.8165,
        "cash_buying_price": 4.8165,
        "spot_selling_price": 4.8488,
        "cash_selling_price": 4.8508,
        "bank_of_china_conversion_price": 4.8116,
        "publish_date": "2023.12.01 09:17:55"
    },
    {
        "currency_name": "JPY",
        "spot_exchange_buying_price": 4.8179,
        "cash_buying_price": 4.8178,
        "spot_selling_price": 4.8502,
        "cash_selling_price": 4.8522,
        "bank_of_china_conversion_price": 4.8116,
        "publish_date": "2023.12.01 09:17:46"
    },
    {
        "currency_name": "JPY",
        "spot_exchange_buying_price": 4.8144,
        "cash_buying_price": 4.8143,
        "spot_selling_price": 4.8466,
        "cash_selling_price": 4.8486,
        "bank_of_china_conversion_price": 4.8362,
        "publish_date": "2023.12.01 08:58:13"
    },
    {
        "currency_name": "JPY",
        "spot_exchange_buying_price": 4.8062,
        "cash_buying_price": 4.8061,
        "spot_selling_price": 4.8384,
        "cash_selling_price": 4.8403,
        "bank_of_china_conversion_price": 4.8362,
        "publish_date": "2023.12.01 07:49:22"
    },
    {
        "currency_name": "JPY",
        "spot_exchange_buying_price": 4.801,
        "cash_buying_price": 4.8009,
        "spot_selling_price": 4.8332,
        "cash_selling_price": 4.8351,
        "bank_of_china_conversion_price": 4.8362,
        "publish_date": "2023.12.01 06:41:02"
    },
    {
        "currency_name": "JPY",
        "spot_exchange_buying_price": 4.7994,
        "cash_buying_price": 4.7993,
        "spot_selling_price": 4.8316,
        "cash_selling_price": 4.8335,
        "bank_of_china_conversion_price": 4.8362,
        "publish_date": "2023.12.01 05:30:00"
    },
    {
        "currency_name": "JPY",
        "spot_exchange_buying_price": 4.7994,
        "cash_buying_price": 4.7993,
        "spot_selling_price": 4.8316,
        "cash_selling_price": 4.8335,
        "bank_of_china_conversion_price": 4.8362,
        "publish_date": "2023.12.01 02:52:06"
    },
    {
        "currency_name": "JPY",
        "spot_exchange_buying_price": 4.8007,
        "cash_buying_price": 4.8006,
        "spot_selling_price": 4.8329,
        "cash_selling_price": 4.8348,
        "bank_of_china_conversion_price": 4.8362,
        "publish_date": "2023.12.01 02:48:59"
    },
    {
        "currency_name": "JPY",
        "spot_exchange_buying_price": 4.8043,
        "cash_buying_price": 4.8042,
        "spot_selling_price": 4.8365,
        "cash_selling_price": 4.8384,
        "bank_of_china_conversion_price": 4.8362,
        "publish_date": "2023.12.01 02:14:20"
    },
    {
        "currency_name": "JPY",
        "spot_exchange_buying_price": 4.801,
        "cash_buying_price": 4.8009,
        "spot_selling_price": 4.8332,
        "cash_selling_price": 4.8351,
        "bank_of_china_conversion_price": 4.8362,
        "publish_date": "2023.12.01 01:59:16"
    },
    {
        "currency_name": "JPY",
        "spot_exchange_buying_price": 4.8062,
        "cash_buying_price": 4.8061,
        "spot_selling_price": 4.8384,
        "cash_selling_price": 4.8403,
        "bank_of_china_conversion_price": 4.8362,
        "publish_date": "2023.12.01 01:40:14"
    },
    {
        "currency_name": "JPY",
        "spot_exchange_buying_price": 4.8088,
        "cash_buying_price": 4.8087,
        "spot_selling_price": 4.841,
        "cash_selling_price": 4.8429,
        "bank_of_china_conversion_price": 4.8362,
        "publish_date": "2023.12.01 01:22:58"
    },
    {
        "currency_name": "JPY",
        "spot_exchange_buying_price": 4.8134,
        "cash_buying_price": 4.8133,
        "spot_selling_price": 4.8456,
        "cash_selling_price": 4.8476,
        "bank_of_china_conversion_price": 4.8362,
        "publish_date": "2023.12.01 00:49:59"
    },
    {
        "currency_name": "JPY",
        "spot_exchange_buying_price": 4.8101,
        "cash_buying_price": 4.81,
        "spot_selling_price": 4.8423,
        "cash_selling_price": 4.8442,
        "bank_of_china_conversion_price": 4.8362,
        "publish_date": "2023.12.01 00:45:41"
    },
    {
        "currency_name": "JPY",
        "spot_exchange_buying_price": 4.8128,
        "cash_buying_price": 4.8127,
        "spot_selling_price": 4.845,
        "cash_selling_price": 4.8469,
        "bank_of_china_conversion_price": 4.8362,
        "publish_date": "2023.12.01 00:30:53"
    },
    {
        "currency_name": "JPY",
        "spot_exchange_buying_price": 4.8128,
        "cash_buying_price": 4.8127,
        "spot_selling_price": 4.845,
        "cash_selling_price": 4.8469,
        "bank_of_china_conversion_price": 4.8362,
        "publish_date": "2023.12.01 00:26:46"
    },
    {
        "currency_name": "JPY",
        "spot_exchange_buying_price": 4.8101,
        "cash_buying_price": 4.81,
        "spot_selling_price": 4.8423,
        "cash_selling_price": 4.8442,
        "bank_of_china_conversion_price": 4.8362,
        "publish_date": "2023.12.01 00:20:46"
    },
    {
        "currency_name": "JPY",
        "spot_exchange_buying_price": 4.8105,
        "cash_buying_price": 4.8104,
        "spot_selling_price": 4.8427,
        "cash_selling_price": 4.8446,
        "bank_of_china_conversion_price": 4.8362,
        "publish_date": "2023.12.01 00:17:23"
    },
    {
        "currency_name": "JPY",
        "spot_exchange_buying_price": 4.8131,
        "cash_buying_price": 4.813,
        "spot_selling_price": 4.8453,
        "cash_selling_price": 4.8472,
        "bank_of_china_conversion_price": 4.8362,
        "publish_date": "2023.12.01 00:08:09"
    },
    {
        "currency_name": "JPY",
        "spot_exchange_buying_price": 4.8114,
        "cash_buying_price": 4.8113,
        "spot_selling_price": 4.8436,
        "cash_selling_price": 4.8455,
        "bank_of_china_conversion_price": 4.8362,
        "publish_date": "2023.12.01 00:00:05"
    },
    {
        "currency_name": "JPY",
        "spot_exchange_buying_price": 4.8114,
        "cash_buying_price": 4.8113,
        "spot_selling_price": 4.8436,
        "cash_selling_price": 4.8455,
        "bank_of_china_conversion_price": 4.8362,
        "publish_date": "2023.11.30 23:58:08"
    },
    {
        "currency_name": "JPY",
        "spot_exchange_buying_price": 4.8098,
        "cash_buying_price": 4.8097,
        "spot_selling_price": 4.842,
        "cash_selling_price": 4.8439,
        "bank_of_china_conversion_price": 4.8362,
        "publish_date": "2023.11.30 23:55:33"
    },
    {
        "currency_name": "JPY",
        "spot_exchange_buying_price": 4.8072,
        "cash_buying_price": 4.8071,
        "spot_selling_price": 4.8394,
        "cash_selling_price": 4.8413,
        "bank_of_china_conversion_price": 4.8362,
        "publish_date": "2023.11.30 23:52:18"
    },
    {
        "currency_name": "JPY",
        "spot_exchange_buying_price": 4.8056,
        "cash_buying_price": 4.8055,
        "spot_selling_price": 4.8378,
        "cash_selling_price": 4.8397,
        "bank_of_china_conversion_price": 4.8362,
        "publish_date": "2023.11.30 23:45:13"
    },
    {
        "currency_name": "JPY",
        "spot_exchange_buying_price": 4.8014,
        "cash_buying_price": 4.8013,
        "spot_selling_price": 4.8336,
        "cash_selling_price": 4.8355,
        "bank_of_china_conversion_price": 4.8362,
        "publish_date": "2023.11.30 23:38:30"
    },
    {
        "currency_name": "JPY",
        "spot_exchange_buying_price": 4.7978,
        "cash_buying_price": 4.7977,
        "spot_selling_price": 4.83,
        "cash_selling_price": 4.8319,
        "bank_of_china_conversion_price": 4.8362,
        "publish_date": "2023.11.30 23:28:18"
    },
    {
        "currency_name": "JPY",
        "spot_exchange_buying_price": 4.7965,
        "cash_buying_price": 4.7964,
        "spot_selling_price": 4.8287,
        "cash_selling_price": 4.8306,
        "bank_of_china_conversion_price": 4.8362,
        "publish_date": "2023.11.30 23:22:59"
    },
    {
        "currency_name": "JPY",
        "spot_exchange_buying_price": 4.7968,
        "cash_buying_price": 4.7967,
        "spot_selling_price": 4.829,
        "cash_selling_price": 4.8309,
        "bank_of_china_conversion_price": 4.8362,
        "publish_date": "2023.11.30 23:11:11"
    },
    {
        "currency_name": "JPY",
        "spot_exchange_buying_price": 4.7984,
        "cash_buying_price": 4.7983,
        "spot_selling_price": 4.8306,
        "cash_selling_price": 4.8325,
        "bank_of_china_conversion_price": 4.8362,
        "publish_date": "2023.11.30 23:04:58"
    },
    {
        "currency_name": "JPY",
        "spot_exchange_buying_price": 4.7968,
        "cash_buying_price": 4.7967,
        "spot_selling_price": 4.829,
        "cash_selling_price": 4.8309,
        "bank_of_china_conversion_price": 4.8362,
        "publish_date": "2023.11.30 22:58:47"
    },
    {
        "currency_name": "JPY",
        "spot_exchange_buying_price": 4.7942,
        "cash_buying_price": 4.7941,
        "spot_selling_price": 4.8264,
        "cash_selling_price": 4.8283,
        "bank_of_china_conversion_price": 4.8362,
        "publish_date": "2023.11.30 22:52:08"
    },
    {
        "currency_name": "JPY",
        "spot_exchange_buying_price": 4.7932,
        "cash_buying_price": 4.7931,
        "spot_selling_price": 4.8254,
        "cash_selling_price": 4.8273,
        "bank_of_china_conversion_price": 4.8362,
        "publish_date": "2023.11.30 22:47:53"
    },
    {
        "currency_name": "JPY",
        "spot_exchange_buying_price": 4.7961,
        "cash_buying_price": 4.796,
        "spot_selling_price": 4.8283,
        "cash_selling_price": 4.8302,
        "bank_of_china_conversion_price": 4.8362,
        "publish_date": "2023.11.30 22:40:50"
    },
    {
        "currency_name": "JPY",
        "spot_exchange_buying_price": 4.8033,
        "cash_buying_price": 4.8032,
        "spot_selling_price": 4.8355,
        "cash_selling_price": 4.8374,
        "bank_of_china_conversion_price": 4.8362,
        "publish_date": "2023.11.30 22:31:20"
    },
    {
        "currency_name": "JPY",
        "spot_exchange_buying_price": 4.8056,
        "cash_buying_price": 4.8055,
        "spot_selling_price": 4.8378,
        "cash_selling_price": 4.8397,
        "bank_of_china_conversion_price": 4.8362,
        "publish_date": "2023.11.30 22:17:34"
    },
    {
        "currency_name": "JPY",
        "spot_exchange_buying_price": 4.8032,
        "cash_buying_price": 4.8031,
        "spot_selling_price": 4.8354,
        "cash_selling_price": 4.8373,
        "bank_of_china_conversion_price": 4.8362,
        "publish_date": "2023.11.30 22:10:04"
    },
    {
        "currency_name": "JPY",
        "spot_exchange_buying_price": 4.8075,
        "cash_buying_price": 4.8074,
        "spot_selling_price": 4.8397,
        "cash_selling_price": 4.8416,
        "bank_of_china_conversion_price": 4.8362,
        "publish_date": "2023.11.30 22:00:44"
    },
    {
        "currency_name": "JPY",
        "spot_exchange_buying_price": 4.8104,
        "cash_buying_price": 4.8103,
        "spot_selling_price": 4.8426,
        "cash_selling_price": 4.8445,
        "bank_of_china_conversion_price": 4.8362,
        "publish_date": "2023.11.30 21:58:52"
    }
]